napari_omaas/__init__.py
napari_omaas/_reader.py
napari_omaas/_sample_data.py
napari_omaas/_widget.py
napari_omaas/_writer.py
napari_omaas/custom_exceptions.py
napari_omaas/napari.yaml
napari_omaas/utils.py
napari_omaas/_tests/__init__.py
napari_omaas/_tests/test_sample_data.py
napari_omaas/_tests/test_widget.py
napari_omaas/_tests/test_writer.py
napari_omaas-1.0.4.dist-info/LICENSE
napari_omaas-1.0.4.dist-info/METADATA
napari_omaas-1.0.4.dist-info/WHEEL
napari_omaas-1.0.4.dist-info/entry_points.txt
napari_omaas-1.0.4.dist-info/top_level.txt
napari_omaas-1.0.4.dist-info/RECORD
