Metadata-Version: 2.2
Name: napari-omaas
Version: 1.0.4
Summary: napari-OMAAS stands for Optical Mapping Acquisition and Analysis Software
Home-page: https://github.com/rjlopez2/napari-omaas
Author: Ruben Lopez
Author-email: rjlopez2@gmail.com
License: BSD-3-Clause
Project-URL: Bug Tracker, https://github.com/rjlopez2/napari-omaas/issues
Project-URL: Documentation, https://github.com/rjlopez2/napari-omaas#README.md
Project-URL: Source Code, https://github.com/rjlopez2/napari-omaas
Project-URL: User Support, https://github.com/rjlopez2/napari-omaas/issues
Classifier: Development Status :: 2 - Pre-Alpha
Classifier: Framework :: napari
Classifier: Intended Audience :: Developers
Classifier: License :: OSI Approved :: BSD License
Classifier: Operating System :: OS Independent
Classifier: Programming Language :: Python
Classifier: Programming Language :: Python :: 3
Classifier: Programming Language :: Python :: 3 :: Only
Classifier: Programming Language :: Python :: 3.10
Classifier: Programming Language :: Python :: 3.11
Classifier: Programming Language :: Python :: 3.12
Classifier: Topic :: Scientific/Engineering :: Image Processing
Requires-Python: >=3.10
License-File: LICENSE
Requires-Dist: numpy
Requires-Dist: tqdm
Requires-Dist: superqt
Requires-Dist: magicgui
Requires-Dist: qtpy
Requires-Dist: opencv-python-headless
Requires-Dist: sif_parser
Requires-Dist: napari_matplotlib
Requires-Dist: napari-tiff
Requires-Dist: napari-mat-file-reader
Requires-Dist: opticalmapping
Requires-Dist: scikit-image
Requires-Dist: matplotlib
Requires-Dist: pandas
Requires-Dist: scipy
Requires-Dist: tifffile
Requires-Dist: toml
Provides-Extra: testing
Requires-Dist: tox; extra == "testing"
Requires-Dist: pytest; extra == "testing"
Requires-Dist: pytest-cov; extra == "testing"
Requires-Dist: pytest-qt; extra == "testing"
Requires-Dist: napari; extra == "testing"
Requires-Dist: pyqt5; extra == "testing"
Provides-Extra: docs
Requires-Dist: sphinx; extra == "docs"
Requires-Dist: sphinxcontrib-napoleon; extra == "docs"
Requires-Dist: sphinxcontrib-bibtex; extra == "docs"
Requires-Dist: sphinxcontrib-video; extra == "docs"
Requires-Dist: sphinx-autobuild; extra == "docs"
Requires-Dist: sphinx-copybutton; extra == "docs"
Requires-Dist: sphinx-codeautolink; extra == "docs"
Requires-Dist: furo; extra == "docs"
Requires-Dist: myst_nb>=1.0.0; extra == "docs"
Requires-Dist: jupytext; extra == "docs"
Requires-Dist: jupyter-cache; extra == "docs"
Provides-Extra: gpu
Requires-Dist: cupy-cuda11x; extra == "gpu"
